fastplus/__init__.py
fastplus/cli.py
fastplus/commands/__init__.py
fastplus/commands/generate.py
fastplus-0.0.1.dist-info/LICENSE.md
fastplus-0.0.1.dist-info/METADATA
fastplus-0.0.1.dist-info/WHEEL
fastplus-0.0.1.dist-info/entry_points.txt
fastplus-0.0.1.dist-info/top_level.txt
fastplus-0.0.1.dist-info/RECORD
