Metadata-Version: 2.1
Name: fastplus
Version: 0.0.1
Summary: An opinionated expansion of FastAPI
Home-page: https://github.com/MetaBytez/fastplus
Author: Will Johns
Author-email: will@wcj.dev
License: UNKNOWN
Platform: UNKNOWN
Classifier: Programming Language :: Python :: 3
Classifier: License :: OSI Approved :: MIT License
Classifier: Operating System :: OS Independent
Requires-Python: >=3.6
Requires-Dist: Click
